README.md
setup.py
commandbus/__init__.py
commandbus/_exception.py
commandbus/_model.py
commandbus.egg-info/PKG-INFO
commandbus.egg-info/SOURCES.txt
commandbus.egg-info/dependency_links.txt
commandbus.egg-info/top_level.txt
test/__init__.py
test/test_functional.py