Metadata-Version: 1.0
Name: commandbus
Version: 1.0.1
Summary: Command Bus Pattern in Python made easy
Home-page: https://github.com/psincraian/commandbus
Author: Petru Rares Sincraian
Author-email: psincraian@gmail.com
License: MIT
Keywords: commandbus command bus python pattern patterns
Platform: UNKNOWN
